impacts_hpc-0.0.6.dist-info/licenses/LICENSE
impactshpc/__init__.py
impactshpc/config.yml
impactshpc/components_data/batteries_impacts.csv
impactshpc/components_data/cooling_specs.csv
impactshpc/components_data/cpu_profile.csv
impactshpc/components_data/factors.yml
impactshpc/components_data/cooling/cooling_impacts.csv
impactshpc/components_data/cooling/extrapolation_factors.csv
impactshpc/components_data/crowdsourcing/ademe_base_impacts_negaoctet.csv
impactshpc/components_data/crowdsourcing/cpu_specs.csv
impactshpc/components_data/crowdsourcing/electrical_mix_impacts_countries.csv
impactshpc/components_data/crowdsourcing/gpu_infos.csv
impactshpc/components_data/crowdsourcing/gpu_specs.csv
impactshpc/components_data/crowdsourcing/iot_factors_tide.csv
impactshpc/components_data/crowdsourcing/ram_manufacture.csv
impactshpc/components_data/crowdsourcing/ssd_manufacture.csv
impactshpc/src/__init__.py
impactshpc/src/battery.py
impactshpc/src/cooling.py
impactshpc/src/cpu.py
impactshpc/src/gpu.py
impactshpc/src/job.py
impactshpc/src/other_components.py
impactshpc/src/park.py
impactshpc/src/ram.py
impactshpc/src/server.py
impactshpc/src/ssd.py
impactshpc/src/core/ReplicableValue.py
impactshpc/src/core/__init__.py
impactshpc/src/core/allocation.py
impactshpc/src/core/config.py
impactshpc/src/core/dateRange.py
impactshpc/src/core/formatters.py
impactshpc/src/core/fuzzymatch.py
impactshpc/src/core/hasConsumptionAndEmbodiedImpacts.py
impactshpc/src/core/hasEmbodiedImpact.py
impactshpc/src/core/impacts.py
impactshpc/src/core/ontology.py
impactshpc/src/core/utils.py
impactshpc/src/core/units/constants_en.txt
impactshpc/src/core/units/units.txt
impacts_hpc-0.0.6.dist-info/METADATA
impacts_hpc-0.0.6.dist-info/WHEEL
impacts_hpc-0.0.6.dist-info/top_level.txt
impacts_hpc-0.0.6.dist-info/RECORD
