Metadata-Version: 2.4
Name: impacts-hpc
Version: 0.0.6
Summary: Impacts-HPC is a Python library designed to estimate the environmental impact of jobs on data centers
Author-email: Valentin Regnault <valentin.regnault@etudiant.univ-rennes.fr>, Gael Guennebaud <gael.guennebaud@inria.fr>, Didier Mallarino <didier.mallarino@osupytheas.fr>, Marius Garénaux Gruau <marius.garenaux-gruau@irisa.fr>
Maintainer-email: Gael Guennebaud <gael.guennebaud@inria.fr>, Didier Mallarino <didier.mallarino@osupytheas.fr>, Marius Garénaux Gruau <marius.garenaux-gruau@irisa.fr>
License-Expression: GPL-3.0-or-later
Project-URL: Documentation, https://impacthpc-cc8227.pages.in2p3.fr/index.html
Project-URL: Repository, https://gitlab.in2p3.fr/impacts-hpc/impacts-hpc
Keywords: environmental impact,green,HPC,green it,data centers,estimation,CO2,carbon footprint,footprint,LCA,IRISA,LogicA
Classifier: Programming Language :: Python :: 3
Classifier: Operating System :: OS Independent
Requires-Python: >=3.12
License-File: LICENSE
Requires-Dist: numpy==2.3.2
Requires-Dist: pandas==2.3.1
Requires-Dist: Pint==0.24.4
Requires-Dist: PyYAML==6.0.2
Requires-Dist: rapidfuzz==3.13.0
Requires-Dist: scipy==1.16.1
Requires-Dist: mip==1.14.2
Dynamic: license-file
